{
"lorcylovesyou|2077835131734118780": {
"username": "lorcylovesyou",
"tweets": [
{
"id": 2077835131734118780,
"conv": "2077835131734118780",
"text": "Hi, I’m Joshua Lorcy!\n\nPokemon VGC player &amp; Community Ambassador with 6 years of tournament experience and 3 years casting grassroots and unofficial Pokemon events.\n\nI enjoy breaking down gameplay while keeping broadcasts engaging for both new and experienced viewers.\n\nDMs open!",
"date": "2026-07-16T19:17:54+00:00",
"url": "https://x.com/lorcylovesyou/status/2077835131734118780",
"media": [
[
"https://video.twimg.com/amplify_video/2077834400788606977/vid/avc1/1920x1080/6DBPShVY1L4AaEes.mp4?tag=29",
"video"
]
]
}
],
"last_fetch": "2026-07-17T00:21:43.763118+00:00"
},
"vgcvictoryroad|2077908640305226228": {
"username": "VGCVictoryRoad",
"tweets": [
{
"id": 2077908640305226228,
"conv": "2077908640305226228",
"text": "This week's mass outbreak event is live! 🛶 #PokemonScarletViolet\n\n🕛 Ends: 6 Aug @ 23:59 UTC\n\n📍 Casseroya Lake\n🎗️ Rowdy Mark: Catch the Rowdy Dondozo\n🎗️ Crafty Mark: Catch the Opportunist Tatsugiri\n🎗️ Ferocious Mark: Catch the Rampaging Veluza\n\n🔗 Info:",
"date": "2026-07-17T00:10:00+00:00",
"url": "https://x.com/VGCVictoryRoad/status/2077908640305226228",
"media": [
[
"https://pbs.twimg.com/media/HNWL987WUAA0BoA.jpg?name=large",
"photo"
]
]
}
],
"last_fetch": "2026-07-17T00:31:40.593200+00:00"
},
"vgcvictoryroad|2077906125043769821": {
"username": "VGCVictoryRoad",
"tweets": [
{
"id": 2077906125043769821,
"conv": "2077906125043769821",
"text": "Take the chance to get Magikarp with Dragon Tera Type in 7★ Tera Raids! 🐟🐲 #PokemonScarletViolet\n\n🕛 Ends: 6 Aug @ 23:59 UTC\n\n▶️ Has the Mightiest Mark\n▶️ Gyarados can be sent to visit #PokemonChampions\n▶️ Only 1 per game, replay for rewards\n\n🔗 Info:",
"date": "2026-07-17T00:00:00+00:00",
"url": "https://x.com/VGCVictoryRoad/status/2077906125043769821",
"media": [
[
"https://pbs.twimg.com/media/HNWJAn8XkAA53Ob.jpg?name=large",
"photo"
]
]
}
],
"last_fetch": "2026-07-17T00:31:40.593200+00:00"
},
"vgcvictoryroad|2077911157109883053": {
"username": "VGCVictoryRoad",
"tweets": [
{
"id": 2077911157109883053,
"conv": "2077911157109883053",
"text": "This week's mass outbreak event is live! 🌊🎗️ #PokemonScarletViolet\n\n🕛 Ends: 6 Aug @ 23:59 UTC\n\n📍 Paldea: Catch Spacey Psyduck and Daydreamer Slowpoke\n📍 Kitakami: Catch Arrogant Feebas and Rampaging Basculin\n📍 Terarium: Catch Scholar Lapras\n\n🔗 Info:",
"date": "2026-07-17T00:20:00+00:00",
"url": "https://x.com/VGCVictoryRoad/status/2077911157109883053",
"media": [
[
"https://pbs.twimg.com/media/HNWMiENXAAAJCcI.jpg?name=large",
"photo"
]
]
}
]
}
}